{
  "response": [
    {
      "maintainer": "dkpost3",
      "oem": "",
      "device": "taoyao",
      "filename": "EvolutionX-14.0-20240608-taoyao-v9.0-Unofficial.zip",
      "download": "https://getfile.dokpub.com/yandex/get/https://disk.yandex.ru/d/vvLxJjObx4QDXg",
      "timestamp": 1717863009,
      "md5": "1556d589372879a1c5a9a0f5d5d93fad",
      "sha256": "a5594924bba8c739a9aa606fdc6bd7d5b82d256ce4671ea4f23dd103ab9be63a",
      "size": 2492328762,
      "version": "9.0",
      "buildtype": "user",
      "forum": "",
      "firmware": "",
      "paypal": "",
      "telegram": "dkpost3"
    }
  ]
}
